pstats_extender/__init__.py
pstats_extender-0.1.4.dist-info/METADATA
pstats_extender-0.1.4.dist-info/WHEEL
pstats_extender-0.1.4.dist-info/licenses/LICENSE
pstats_extender-0.1.4.dist-info/RECORD
