Metadata-Version: 2.4
Name: pstats_extender
Version: 0.1.4
Summary: Designed to save pstats log to folder.
License: GNU
License-File: LICENSE
Keywords: pstats,profiler
Author: Kostiantyn Shmyhelskyi
Author-email: graflearnt@gmail.com
Requires-Python: >=3.10,<4.0
Classifier: Development Status :: 5 - Production/Stable
Classifier: License :: Other/Proprietary License
Classifier: Programming Language :: Python :: 3
Classifier: Programming Language :: Python :: 3.10
Classifier: Programming Language :: Python :: 3.11
Classifier: Programming Language :: Python :: 3.12
Classifier: Programming Language :: Python :: 3.13
Classifier: Programming Language :: Python :: 3.14
Classifier: Topic :: Software Development :: Debuggers
Project-URL: Documentation, https://graflearnt.github.io/pstats_extender/pstats_extender.html
Project-URL: Homepage, https://github.com/GrafLearnt/pstats_extender
